agent_builder/__init__.py
agent_builder/agents/__init__.py
agent_builder/agents/agent.py
agent_builder/agents/voice_agent.py
agent_builder/builders/__init__.py
agent_builder/builders/agent_builder.py
agent_builder/builders/base_builder.py
agent_builder/builders/tool_builder.py
agent_builder/builders/voice_agent_builder.py
agent_builder/config/default.py
agent_builder/utils/araise_tool_exception_on_fail.py
agent_builder/utils/audio_utils.py
agent_builder/utils/call_end_exception.py
agent_builder/utils/raise_tool_exception_on_fail.py
agent_builder/utils/websocket_connection.py
backup/remo.py
backup/sample.py
build/lib/agent_builder/__init__.py
build/lib/agent_builder/agents/__init__.py
build/lib/agent_builder/agents/agent.py
build/lib/agent_builder/agents/voice_agent.py
build/lib/agent_builder/builders/__init__.py
build/lib/agent_builder/builders/agent_builder.py
build/lib/agent_builder/builders/base_builder.py
build/lib/agent_builder/builders/tool_builder.py
build/lib/agent_builder/builders/voice_agent_builder.py
build/lib/agent_builder/utils/araise_tool_exception_on_fail.py
build/lib/agent_builder/utils/audio_utils.py
build/lib/agent_builder/utils/call_end_exception.py
build/lib/agent_builder/utils/raise_tool_exception_on_fail.py
build/lib/agent_builder/utils/websocket_connection.py
build/lib/backup/remo.py
build/lib/backup/sample.py
build/lib/build/lib/agent_builder/__init__.py
build/lib/build/lib/agent_builder/agents/__init__.py
build/lib/build/lib/agent_builder/agents/agent.py
build/lib/build/lib/agent_builder/agents/voice_agent.py
build/lib/build/lib/agent_builder/builders/__init__.py
build/lib/build/lib/agent_builder/builders/agent_builder.py
build/lib/build/lib/agent_builder/builders/base_builder.py
build/lib/build/lib/agent_builder/builders/tool_builder.py
build/lib/build/lib/agent_builder/builders/voice_agent_builder.py
build/lib/build/lib/agent_builder/utils/araise_tool_exception_on_fail.py
build/lib/build/lib/agent_builder/utils/audio_utils.py
agent_builder-0.1.7.dist-info/LICENSE
agent_builder-0.1.7.dist-info/METADATA
agent_builder-0.1.7.dist-info/WHEEL
agent_builder-0.1.7.dist-info/top_level.txt
agent_builder-0.1.7.dist-info/RECORD
